LICENSE
MANIFEST.in
README.rst
setup.cfg
setup.py
apistar_auth/__init__.py
apistar_auth/auth.py
apistar_auth/cookies.py
apistar_auth/guid.py
apistar_auth/hasher.py
apistar_auth/login.py
apistar_auth/models.py
apistar_auth/tokens.py
apistar_auth/users.py
apistar_auth/validators.py
apistar_auth.egg-info/PKG-INFO
apistar_auth.egg-info/SOURCES.txt
apistar_auth.egg-info/dependency_links.txt
apistar_auth.egg-info/requires.txt
apistar_auth.egg-info/top_level.txt